examples/example01/test_src.py
examples/example01/src/__init__.py
pytest_pitch/__init__.py
pytest_pitch/khuller_moss_naor.py
pytest_pitch/plugin.py
scripts/benchmark_vs_project.py
pytest_pitch-1.0.5.dist-info/LICENSE
pytest_pitch-1.0.5.dist-info/METADATA
pytest_pitch-1.0.5.dist-info/WHEEL
pytest_pitch-1.0.5.dist-info/entry_points.txt
pytest_pitch-1.0.5.dist-info/top_level.txt
pytest_pitch-1.0.5.dist-info/RECORD
