Metadata-Version: 2.1
Name: pytest-pitch
Version: 1.0.5
Summary: runs tests in an order such that coverage increases as fast as possible
Home-page: https://github.com/mikamove/pytest-pitch
Author: Clemens Löbner
Author-email: mikamove@posteo.de
Maintainer: Clemens Löbner
Maintainer-email: mikamove@posteo.de
License: MIT
Classifier: Development Status :: 4 - Beta
Classifier: Framework :: Pytest
Classifier: Intended Audience :: Developers
Classifier: Topic :: Software Development :: Testing
Classifier: Programming Language :: Python
Classifier: Programming Language :: Python :: 3
Classifier: Programming Language :: Python :: 3.8
Classifier: Programming Language :: Python :: 3.9
Classifier: Programming Language :: Python :: 3.10
Classifier: Programming Language :: Python :: 3 :: Only
Classifier: Programming Language :: Python :: Implementation :: CPython
Classifier: Programming Language :: Python :: Implementation :: PyPy
Classifier: Operating System :: OS Independent
Classifier: License :: OSI Approved :: MIT License
Requires-Python: >=3.8
License-File: LICENSE
Requires-Dist: pytest >=7.3.1
Requires-Dist: pytest-donde >=1.1.0
